{
  "model_type": "dkl",
  "date": "2022/08/05 11:34:58",
  "config": {
    "fold": 0,
    "folds": 5,
    "n_train": 31000,
    "device_type": "cuda",
    "decay": 0.9985,
    "n_max": 12,
    "l_max": 6,
    "train_on_equal_cns": false,
    "lr": 0.00020195001542961622,
    "depth": 3,
    "width": 6227,
    "last_width": 378,
    "activation": "tanh",
    "epochs": 4000,
    "activate_last": true,
    "m_sparse": 912,
    "batchsize": 3111,
    "early_stopping": 250
  },
  "results": {
    "train_duration": 2318.290798460599,
    "testing": {
      "test_set": {
        "duration": 8.154920246917754,
        "mae": 0.03667240962386131,
        "n_test": 264000,
        "cn_2_mae": 0.11065564304590225,
        "cn_3_mae": 0.03274424374103546,
        "cn_4_mae": 0.03319070115685463
      },
      "train_set": {
        "duration": 0.9558523749001324,
        "mae": 0.018379153683781624,
        "n_test": 31000,
        "cn_2_mae": 0.023652106523513794,
        "cn_3_mae": 0.016484785825014114,
        "cn_4_mae": 0.023316456004977226
      }
    }
  }
}