{
  "model_type": "gpr",
  "date": "2022/08/09 15:54:09",
  "config": {
    "fold": 2,
    "folds": 5,
    "m_sparse": 20000,
    "n_train": 3100,
    "noise": 0.01,
    "n_max": 12,
    "l_max": 6,
    "train_on_equal_cns": false
  },
  "results": {
    "train_duration": 38.84213003516197,
    "testing": {
      "test_set": {
        "duration": 202.68565559573472,
        "mae": 0.03793445774460883,
        "n_test": 264000,
        "cn_2_mae": 0.14808947339961723,
        "cn_3_mae": 0.03367013726150861,
        "cn_4_mae": 0.03580261045614343
      },
      "train_set": {
        "duration": 2.3935309555381536,
        "mae": 0.016219683971385644,
        "n_test": 3100,
        "cn_2_mae": 0.004644076483705523,
        "cn_3_mae": 0.014912230026255201,
        "cn_4_mae": 0.022273518959660774
      }
    }
  }
}