{
  "model_type": "gpr",
  "date": "2022/09/22 14:16:04",
  "config": {
    "fold": 4,
    "folds": 5,
    "m_sparse": 5000,
    "n_train": 310,
    "noise": 0.01,
    "n_max": 10,
    "l_max": 8,
    "train_on_equal_cns": false
  },
  "results": {
    "train_duration": 0.0871523804962635,
    "testing": {
      "test_set": {
        "duration": 9.885783867910504,
        "mae": 0.12596480452077705,
        "n_test": 264000,
        "cn_2_mae": 0.1454826014227775,
        "cn_3_mae": 0.11338618812290188,
        "cn_4_mae": 0.10795119270434352
      },
      "train_set": {
        "duration": 0.015508072450757027,
        "mae": 0.006502837132062807,
        "n_test": 310,
        "cn_2_mae": 0.0058979157400008385,
        "cn_3_mae": 0.0056041060353367,
        "cn_4_mae": 0.013783826943823433
      }
    }
  }
}