{
  "model_type": "gpr",
  "date": "2022/09/26 13:13:54",
  "config": {
    "fold": 4,
    "folds": 5,
    "m_sparse": 5000,
    "n_train": 31000,
    "noise": 0.01,
    "n_max": 12,
    "l_max": 8,
    "train_on_equal_cns": true
  },
  "results": {
    "train_duration": 475.3618086054921,
    "testing": {
      "test_set": {
        "duration": 371.4180934149772,
        "mae": 0.020469508638822322,
        "n_test": 264000,
        "cn_2_mae": 0.022837385749570203,
        "cn_3_mae": 0.018041806058400296,
        "cn_4_mae": 0.022554600344311317
      },
      "train_set": {
        "duration": 43.58787666447461,
        "mae": 0.018112255878244096,
        "n_test": 30999,
        "cn_2_mae": 0.01775782606679271,
        "cn_3_mae": 0.015189422712348714,
        "cn_4_mae": 0.021389518855590862
      }
    }
  }
}