{
  "model_type": "gpr",
  "date": "2022/08/03 11:38:58",
  "config": {
    "fold": 4,
    "folds": 5,
    "m_sparse": 5000,
    "n_train": 310,
    "noise": 0.01,
    "n_max": 8,
    "l_max": 4,
    "train_on_equal_cns": false
  },
  "results": {
    "train_duration": 0.037909576669335365,
    "testing": {
      "test_set": {
        "duration": 4.36587399430573,
        "mae": 0.14889453334934527,
        "n_test": 264000,
        "cn_2_mae": 0.5220027867378083,
        "cn_3_mae": 0.1278604070741939,
        "cn_4_mae": 0.13138214356719097
      },
      "train_set": {
        "duration": 0.00539252907037735,
        "mae": 0.01937913424045262,
        "n_test": 310,
        "cn_2_mae": 0.004453341286190238,
        "cn_3_mae": 0.014463294941705104,
        "cn_4_mae": 0.041625705282027164
      }
    }
  }
}