{
  "model_type": "gpr",
  "date": "2022/11/02 08:09:55",
  "config": {
    "fold": 1,
    "folds": 5,
    "m_sparse": 5001,
    "n_train": 5000,
    "noise": 0.215,
    "n_max": 12,
    "l_max": 6,
    "train_on_equal_cns": false
  },
  "results": {
    "train_duration": 120.93921760097146,
    "testing": {
      "test_set": {
        "duration": 364.99944994971156,
        "mae": 0.0651844766725656,
        "n_test": 264000,
        "cn_2_mae": 0.07093181574051746,
        "cn_3_mae": 0.058853440582893525,
        "cn_4_mae": 0.07219272720468173
      },
      "train_set": {
        "duration": 7.175216235220432,
        "mae": 0.05841215727804981,
        "n_test": 5000,
        "cn_2_mae": 0.06148394448321877,
        "cn_3_mae": 0.054217741789390934,
        "cn_4_mae": 0.07051685018780741
      }
    }
  }
}