{
  "model_type": "gpr",
  "date": "2022/07/28 12:56:43",
  "config": {
    "fold": 0,
    "folds": 5,
    "m_sparse": 5000,
    "n_train": 5000,
    "noise": 0.000215,
    "n_max": 12,
    "l_max": 6,
    "train_on_equal_cns": false
  },
  "results": {
    "train_duration": 182.82790634036064,
    "testing": {
      "test_set": {
        "duration": 536.4832012355328,
        "mae": 0.0793752086494342,
        "n_test": 264000,
        "cn_2_mae": 0.4155304075814894,
        "cn_3_mae": 0.06567902552766064,
        "cn_4_mae": 0.04962199546792115
      },
      "train_set": {
        "duration": 10.505652595311403,
        "mae": 0.0008797409063365251,
        "n_test": 5000,
        "cn_2_mae": 7.869272261293571e-05,
        "cn_3_mae": 0.0006651311807075698,
        "cn_4_mae": 0.0017009497700482658
      }
    }
  }
}