{
  "model_type": "gpr",
  "date": "2022/11/01 04:23:16",
  "config": {
    "fold": 2,
    "folds": 5,
    "m_sparse": 5000,
    "n_train": 1000000,
    "noise": 1.0,
    "n_max": 12,
    "l_max": 6,
    "train_on_equal_cns": false
  },
  "results": {
    "train_duration": 12883.846792548895,
    "testing": {
      "test_set": {
        "duration": 370.1394836604595,
        "mae": 0.039719827438081,
        "n_test": 264000,
        "cn_2_mae": 0.041382541801012,
        "cn_3_mae": 0.03707470884256532,
        "cn_4_mae": 0.0455081232441865
      },
      "train_set": {
        "duration": 1404.811383254826,
        "mae": 0.04075837256759241,
        "n_test": 1000000,
        "cn_2_mae": 0.04347844046947541,
        "cn_3_mae": 0.037622918384346886,
        "cn_4_mae": 0.04474825373511842
      }
    }
  }
}