{
  "model_type": "gpr",
  "date": "2022/11/01 03:22:51",
  "config": {
    "fold": 2,
    "folds": 5,
    "m_sparse": 5000,
    "n_train": 1000000,
    "noise": 0.01,
    "n_max": 12,
    "l_max": 6,
    "train_on_equal_cns": false
  },
  "results": {
    "train_duration": 14421.077619608492,
    "testing": {
      "test_set": {
        "duration": 382.67605241015553,
        "mae": 0.023512144249787783,
        "n_test": 264000,
        "cn_2_mae": 0.024561010317057447,
        "cn_3_mae": 0.022188490433993204,
        "cn_4_mae": 0.025974448806084
      },
      "train_set": {
        "duration": 1449.4120456688106,
        "mae": 0.02390941440701527,
        "n_test": 1000000,
        "cn_2_mae": 0.02540069837297983,
        "cn_3_mae": 0.02229516003952537,
        "cn_4_mae": 0.025685596517906074
      }
    }
  }
}