{
  "model_type": "gpr",
  "date": "2022/08/10 07:09:39",
  "config": {
    "fold": 0,
    "folds": 5,
    "m_sparse": 200,
    "n_train": 310,
    "noise": 0.01,
    "n_max": 12,
    "l_max": 6,
    "train_on_equal_cns": false
  },
  "results": {
    "train_duration": 0.04451172426342964,
    "testing": {
      "test_set": {
        "duration": 6.191199127584696,
        "mae": 0.14536326739548977,
        "n_test": 264000,
        "cn_2_mae": 0.5250207825258523,
        "cn_3_mae": 0.1280244711584615,
        "cn_4_mae": 0.12185238868165951
      },
      "train_set": {
        "duration": 0.008513443171977997,
        "mae": 0.04526301322586463,
        "n_test": 310,
        "cn_2_mae": 0.22383826537142998,
        "cn_3_mae": 0.03546305629439335,
        "cn_4_mae": 0.05611859117228208
      }
    }
  }
}