{
  "model_type": "gpr",
  "date": "2022/08/10 06:59:10",
  "config": {
    "fold": 0,
    "folds": 5,
    "m_sparse": 1000,
    "n_train": 100000,
    "noise": 0.01,
    "n_max": 12,
    "l_max": 6,
    "train_on_equal_cns": false
  },
  "results": {
    "train_duration": 86.08869338780642,
    "testing": {
      "test_set": {
        "duration": 35.336877934634686,
        "mae": 0.04213002075027509,
        "n_test": 264000,
        "cn_2_mae": 0.18988675433161606,
        "cn_3_mae": 0.034960778431838424,
        "cn_4_mae": 0.03373792072232021
      },
      "train_set": {
        "duration": 13.237925715744495,
        "mae": 0.04029206259838249,
        "n_test": 100000,
        "cn_2_mae": 0.19086119146217934,
        "cn_3_mae": 0.033671200609754384,
        "cn_4_mae": 0.033506508527031735
      }
    }
  }
}