{
  "model_type": "gpr",
  "date": "2022/08/09 18:44:54",
  "config": {
    "fold": 4,
    "folds": 5,
    "m_sparse": 10000,
    "n_train": 10000,
    "noise": 0.01,
    "n_max": 12,
    "l_max": 6,
    "train_on_equal_cns": false
  },
  "results": {
    "train_duration": 901.4642186872661,
    "testing": {
      "test_set": {
        "duration": 1227.8371451925486,
        "mae": 0.030611113390186698,
        "n_test": 264000,
        "cn_2_mae": 0.07571760112930842,
        "cn_3_mae": 0.027618810360046646,
        "cn_4_mae": 0.02981284438589388
      },
      "train_set": {
        "duration": 46.82950405217707,
        "mae": 0.018705706846299363,
        "n_test": 10000,
        "cn_2_mae": 0.009197557960016695,
        "cn_3_mae": 0.01752095958719534,
        "cn_4_mae": 0.024443575279296397
      }
    }
  }
}