{
  "model_type": "gpr",
  "date": "2022/07/31 19:55:55",
  "config": {
    "fold": 3,
    "folds": 5,
    "m_sparse": 100,
    "n_train": 3100,
    "noise": 0.01,
    "n_max": 8,
    "l_max": 8,
    "train_on_equal_cns": false
  },
  "results": {
    "train_duration": 0.14508046582341194,
    "testing": {
      "test_set": {
        "duration": 3.474666276946664,
        "mae": 0.22018269711524222,
        "n_test": 264000,
        "cn_2_mae": 0.6416460864860482,
        "cn_3_mae": 0.20619540526067387,
        "cn_4_mae": 0.1915679721445331
      },
      "train_set": {
        "duration": 0.034341635182499886,
        "mae": 0.21028736802448067,
        "n_test": 3100,
        "cn_2_mae": 0.6136421218605075,
        "cn_3_mae": 0.1944131589740876,
        "cn_4_mae": 0.18374327028482582
      }
    }
  }
}