{
  "model_type": "gpr",
  "date": "2022/08/09 16:30:45",
  "config": {
    "fold": 0,
    "folds": 5,
    "m_sparse": 20000,
    "n_train": 10000,
    "noise": 0.01,
    "n_max": 12,
    "l_max": 6,
    "train_on_equal_cns": false
  },
  "results": {
    "train_duration": 1163.0117271859199,
    "testing": {
      "test_set": {
        "duration": 1755.8624647408724,
        "mae": 0.030012010895132352,
        "n_test": 264000,
        "cn_2_mae": 0.07642671704675998,
        "cn_3_mae": 0.02698201290643329,
        "cn_4_mae": 0.029639150826931582
      },
      "train_set": {
        "duration": 66.72281975485384,
        "mae": 0.019024385746724097,
        "n_test": 10000,
        "cn_2_mae": 0.009197089434299371,
        "cn_3_mae": 0.017806285645380848,
        "cn_4_mae": 0.02458372034659952
      }
    }
  }
}