{
  "model_type": "gpr",
  "date": "2022/08/10 07:26:13",
  "config": {
    "fold": 0,
    "folds": 5,
    "m_sparse": 100,
    "n_train": 31000,
    "noise": 0.01,
    "n_max": 12,
    "l_max": 6,
    "train_on_equal_cns": false
  },
  "results": {
    "train_duration": 1.6057644821703434,
    "testing": {
      "test_set": {
        "duration": 3.8295803107321262,
        "mae": 0.14444428002604628,
        "n_test": 264000,
        "cn_2_mae": 0.4927951146509648,
        "cn_3_mae": 0.12278369502597444,
        "cn_4_mae": 0.14095264906245925
      },
      "train_set": {
        "duration": 0.4717963505536318,
        "mae": 0.14246565282033502,
        "n_test": 31000,
        "cn_2_mae": 0.4780025043401938,
        "cn_3_mae": 0.12335627168540066,
        "cn_4_mae": 0.13823573503592537
      }
    }
  }
}