{
  "model_type": "gpr",
  "date": "2022/09/23 11:03:26",
  "config": {
    "fold": 3,
    "folds": 5,
    "m_sparse": 5000,
    "n_train": 100,
    "noise": 0.01,
    "n_max": 12,
    "l_max": 5,
    "train_on_equal_cns": false
  },
  "results": {
    "train_duration": 0.012775806710124016,
    "testing": {
      "test_set": {
        "duration": 3.8352226447314024,
        "mae": 0.18898191705149725,
        "n_test": 264000,
        "cn_2_mae": 0.20731276525264397,
        "cn_3_mae": 0.18094056583984225,
        "cn_4_mae": 0.16111880653175603
      },
      "train_set": {
        "duration": 0.0022558923810720444,
        "mae": 0.00220395101942529,
        "n_test": 100,
        "cn_2_mae": 0.0020550889045462435,
        "cn_3_mae": 0.0019425817538600671,
        "cn_4_mae": 0.00514562100056537
      }
    }
  }
}