{
  "model_type": "gpr",
  "date": "2022/07/19 11:22:33",
  "config": {
    "fold": 0,
    "folds": 5,
    "m_sparse": 10,
    "n_train": 1000000,
    "noise": 0.001,
    "n_max": 11,
    "l_max": 4,
    "train_on_equal_cns": false
  },
  "results": {
    "train_duration": 10.068867491558194,
    "testing": {
      "test_set": {
        "duration": 1.0514002088457346,
        "mae": 0.4262505989594262,
        "n_test": 264000,
        "cn_2_mae": 0.8760844583267847,
        "cn_3_mae": 0.41637908313710803,
        "cn_4_mae": 0.35703793729630084
      },
      "train_set": {
        "duration": 4.1592973954975605,
        "mae": 0.42210785334629136,
        "n_test": 1000000,
        "cn_2_mae": 0.9076104599078425,
        "cn_3_mae": 0.4161072338020518,
        "cn_4_mae": 0.35039522765294717
      }
    }
  }
}