{
  "model_type": "gpr",
  "date": "2022/08/10 11:08:03",
  "config": {
    "fold": 4,
    "folds": 5,
    "m_sparse": 500,
    "n_train": 100000,
    "noise": 0.01,
    "n_max": 12,
    "l_max": 6,
    "train_on_equal_cns": false
  },
  "results": {
    "train_duration": 29.430687265470624,
    "testing": {
      "test_set": {
        "duration": 15.03047502413392,
        "mae": 0.06480178233688563,
        "n_test": 264000,
        "cn_2_mae": 0.2752556829432734,
        "cn_3_mae": 0.05515135538603016,
        "cn_4_mae": 0.047496220044371235
      },
      "train_set": {
        "duration": 5.5029613841325045,
        "mae": 0.0586385737300108,
        "n_test": 100000,
        "cn_2_mae": 0.25195050742612,
        "cn_3_mae": 0.05158202538910022,
        "cn_4_mae": 0.04677284138312152
      }
    }
  }
}