{
  "model_type": "gpr",
  "date": "2022/07/28 07:55:47",
  "config": {
    "fold": 3,
    "folds": 5,
    "m_sparse": 5000,
    "n_train": 1000,
    "noise": 0.215,
    "n_max": 12,
    "l_max": 6,
    "train_on_equal_cns": false
  },
  "results": {
    "train_duration": 2.4564235396683216,
    "testing": {
      "test_set": {
        "duration": 47.09714267589152,
        "mae": 0.09757758552343963,
        "n_test": 264000,
        "cn_2_mae": 0.21945501005466828,
        "cn_3_mae": 0.08270923943402941,
        "cn_4_mae": 0.11759793376189964
      },
      "train_set": {
        "duration": 0.17152093164622784,
        "mae": 0.07701801408676605,
        "n_test": 1000,
        "cn_2_mae": 0.07107263291159054,
        "cn_3_mae": 0.06935150389035537,
        "cn_4_mae": 0.10525882897681615
      }
    }
  }
}