{
  "model_type": "nn",
  "date": "2022/08/01 02:14:53",
  "config": {
    "fold": 4,
    "folds": 5,
    "n_train": 10000,
    "batchsize": 1000,
    "device_type": "cuda",
    "n_max": 12,
    "l_max": 6,
    "train_on_equal_cns": false,
    "lr": 0.00017844777577213656,
    "depth": 5,
    "width": 3321,
    "activation": "celu",
    "epochs": 2932,
    "decay": 1.0077387662718018
  },
  "results": {
    "train_duration": 888.7499042777345,
    "testing": {
      "test_set": {
        "duration": 0.0008417791686952114,
        "mae": 0.06495536863803864,
        "n_test": 264000,
        "cn_2_mae": 0.17703309655189514,
        "cn_3_mae": 0.05806374549865723,
        "cn_4_mae": 0.06108921021223068
      },
      "train_set": {
        "duration": 0.000494473148137331,
        "mae": 0.0434577502310276,
        "n_test": 10000,
        "cn_2_mae": 0.06966102123260498,
        "cn_3_mae": 0.04016830399632454,
        "cn_4_mae": 0.04950457066297531
      }
    }
  }
}