{
  "model_type": "nn",
  "date": "2022/07/30 13:04:39",
  "config": {
    "fold": 1,
    "folds": 5,
    "n_train": 10000,
    "batchsize": 1000,
    "device_type": "cuda",
    "n_max": 12,
    "l_max": 6,
    "train_on_equal_cns": false,
    "lr": 0.0009223095289646682,
    "depth": 6,
    "width": 483,
    "activation": "celu",
    "epochs": 3338,
    "decay": 0.9965533172423096
  },
  "results": {
    "train_duration": 273.45884123211727,
    "testing": {
      "test_set": {
        "duration": 0.0004387139342725277,
        "mae": 0.053322695195674896,
        "n_test": 264000,
        "cn_2_mae": 0.17201507091522217,
        "cn_3_mae": 0.04873446002602577,
        "cn_4_mae": 0.04620747268199921
      },
      "train_set": {
        "duration": 0.0004220162518322468,
        "mae": 0.0017427089624106884,
        "n_test": 10000,
        "cn_2_mae": 0.0005712772835977376,
        "cn_3_mae": 0.0014322423376142979,
        "cn_4_mae": 0.0029946668073534966
      }
    }
  }
}