{
  "model_type": "nn",
  "date": "2022/08/01 05:27:38",
  "config": {
    "fold": 1,
    "folds": 5,
    "n_train": 10000,
    "batchsize": 1000,
    "device_type": "cuda",
    "n_max": 12,
    "l_max": 6,
    "train_on_equal_cns": false,
    "lr": 0.0007876629629187071,
    "depth": 3,
    "width": 2769,
    "activation": "celu",
    "epochs": 2599,
    "decay": 0.9856790629075186
  },
  "results": {
    "train_duration": 347.4235264142044,
    "testing": {
      "test_set": {
        "duration": 0.0005159433931112289,
        "mae": 0.07178469002246857,
        "n_test": 264000,
        "cn_2_mae": 0.20382899045944214,
        "cn_3_mae": 0.06572383642196655,
        "cn_4_mae": 0.06658440828323364
      },
      "train_set": {
        "duration": 0.0003365371376276016,
        "mae": 0.054690416902303696,
        "n_test": 10000,
        "cn_2_mae": 0.08669360727071762,
        "cn_3_mae": 0.051233112812042236,
        "cn_4_mae": 0.05942501872777939
      }
    }
  }
}