{
  "model_type": "nn",
  "date": "2022/08/01 05:27:39",
  "config": {
    "fold": 1,
    "folds": 5,
    "n_train": 10000,
    "batchsize": 1000,
    "device_type": "cuda",
    "n_max": 12,
    "l_max": 6,
    "train_on_equal_cns": false,
    "lr": 0.0005579588696881601,
    "depth": 1,
    "width": 520,
    "activation": "celu",
    "epochs": 3067,
    "decay": 0.9899697029079607
  },
  "results": {
    "train_duration": 193.99821116868407,
    "testing": {
      "test_set": {
        "duration": 0.00014266232028603554,
        "mae": 0.062197789549827576,
        "n_test": 264000,
        "cn_2_mae": 0.18383879959583282,
        "cn_3_mae": 0.05640444904565811,
        "cn_4_mae": 0.0578933022916317
      },
      "train_set": {
        "duration": 0.00016932515427470207,
        "mae": 0.0390169583261013,
        "n_test": 10000,
        "cn_2_mae": 0.043753668665885925,
        "cn_3_mae": 0.03603644669055939,
        "cn_4_mae": 0.04771081730723381
      }
    }
  }
}