{
  "model_type": "nn",
  "date": "2022/07/30 16:39:57",
  "config": {
    "fold": 2,
    "folds": 5,
    "n_train": 10000,
    "batchsize": 1000,
    "device_type": "cuda",
    "n_max": 12,
    "l_max": 6,
    "train_on_equal_cns": false,
    "lr": 0.0009645077783552574,
    "depth": 1,
    "width": 588,
    "activation": "celu",
    "epochs": 1167,
    "decay": 0.9894073552822188
  },
  "results": {
    "train_duration": 116.08130803704262,
    "testing": {
      "test_set": {
        "duration": 0.00019480101764202118,
        "mae": 0.058940041810274124,
        "n_test": 264000,
        "cn_2_mae": 0.16322505474090576,
        "cn_3_mae": 0.054700370877981186,
        "cn_4_mae": 0.05713982135057449
      },
      "train_set": {
        "duration": 0.0002378649078309536,
        "mae": 0.036119766533374786,
        "n_test": 10000,
        "cn_2_mae": 0.03789372369647026,
        "cn_3_mae": 0.03315741941332817,
        "cn_4_mae": 0.044724706560373306
      }
    }
  }
}