{
  "model_type": "nn",
  "date": "2022/07/28 08:39:18",
  "config": {
    "fold": 4,
    "folds": 5,
    "n_train": 1000,
    "batchsize": 1000,
    "device_type": "cuda",
    "n_max": 12,
    "l_max": 6,
    "train_on_equal_cns": false,
    "lr": 0.00032169562531046946,
    "depth": 5,
    "width": 73,
    "activation": "celu",
    "epochs": 2762,
    "decay": 0.9924559770921688
  },
  "results": {
    "train_duration": 33.9836015640758,
    "testing": {
      "test_set": {
        "duration": 0.0005447668954730034,
        "mae": 0.12928679585456848,
        "n_test": 264000,
        "cn_2_mae": 0.3527834117412567,
        "cn_3_mae": 0.11930415034294128,
        "cn_4_mae": 0.1097007468342781
      },
      "train_set": {
        "duration": 0.000625288113951683,
        "mae": 0.04650367796421051,
        "n_test": 1000,
        "cn_2_mae": 0.041347749531269073,
        "cn_3_mae": 0.042005058377981186,
        "cn_4_mae": 0.06202970817685127
      }
    }
  }
}