{
  "model_type": "nn",
  "date": "2022/07/28 10:11:22",
  "config": {
    "fold": 4,
    "folds": 5,
    "n_train": 1000,
    "batchsize": 1000,
    "device_type": "cuda",
    "n_max": 12,
    "l_max": 6,
    "train_on_equal_cns": false,
    "lr": 0.00018703333726484086,
    "depth": 4,
    "width": 88,
    "activation": "relu",
    "epochs": 3131,
    "decay": 0.9937319235876426
  },
  "results": {
    "train_duration": 42.336422488093376,
    "testing": {
      "test_set": {
        "duration": 0.0004859080072492361,
        "mae": 0.17138177156448364,
        "n_test": 264000,
        "cn_2_mae": 0.4712589383125305,
        "cn_3_mae": 0.1579045057296753,
        "cn_4_mae": 0.14539068937301636
      },
      "train_set": {
        "duration": 0.0006199351046234369,
        "mae": 0.024725591763854027,
        "n_test": 1000,
        "cn_2_mae": 0.013408031314611435,
        "cn_3_mae": 0.02097715064883232,
        "cn_4_mae": 0.03893633559346199
      }
    }
  }
}