{
  "model_type": "nn",
  "date": "2022/07/28 08:56:03",
  "config": {
    "fold": 3,
    "folds": 5,
    "n_train": 1000,
    "batchsize": 1000,
    "device_type": "cuda",
    "n_max": 12,
    "l_max": 6,
    "train_on_equal_cns": false,
    "lr": 0.0008293313679675249,
    "depth": 3,
    "width": 89,
    "activation": "relu",
    "epochs": 216,
    "decay": 0.9934548823420467
  },
  "results": {
    "train_duration": 6.273750339169055,
    "testing": {
      "test_set": {
        "duration": 0.00033898488618433475,
        "mae": 0.1541651487350464,
        "n_test": 264000,
        "cn_2_mae": 0.4452257752418518,
        "cn_3_mae": 0.138694167137146,
        "cn_4_mae": 0.14898841083049774
      },
      "train_set": {
        "duration": 0.00035249278880655766,
        "mae": 0.009680848568677902,
        "n_test": 1000,
        "cn_2_mae": 0.004528856370598078,
        "cn_3_mae": 0.008673826232552528,
        "cn_4_mae": 0.014229354448616505
      }
    }
  }
}