{
  "model_type": "nn",
  "date": "2022/07/28 12:00:19",
  "config": {
    "fold": 0,
    "folds": 5,
    "n_train": 10000,
    "batchsize": 1000,
    "device_type": "cuda",
    "n_max": 12,
    "l_max": 6,
    "train_on_equal_cns": false,
    "lr": 0.00018547384722337077,
    "depth": 5,
    "width": 81,
    "activation": "tanh",
    "epochs": 487,
    "decay": 0.9948991560549819
  },
  "results": {
    "train_duration": 98.32045043702237,
    "testing": {
      "test_set": {
        "duration": 0.0015368598978966475,
        "mae": 0.08072545379400253,
        "n_test": 264000,
        "cn_2_mae": 0.22511039674282074,
        "cn_3_mae": 0.07552076876163483,
        "cn_4_mae": 0.06571236252784729
      },
      "train_set": {
        "duration": 0.00032429490238428116,
        "mae": 0.048784755170345306,
        "n_test": 10000,
        "cn_2_mae": 0.048473019152879715,
        "cn_3_mae": 0.047212906181812286,
        "cn_4_mae": 0.05347141623497009
      }
    }
  }
}