{
  "model_type": "nn",
  "date": "2022/07/28 08:39:07",
  "config": {
    "fold": 1,
    "folds": 5,
    "n_train": 1000,
    "batchsize": 1000,
    "device_type": "cuda",
    "n_max": 12,
    "l_max": 6,
    "train_on_equal_cns": false,
    "lr": 0.0007815409542106165,
    "depth": 2,
    "width": 95,
    "activation": "tanh",
    "epochs": 831,
    "decay": 0.9992999997723628
  },
  "results": {
    "train_duration": 15.777646586066112,
    "testing": {
      "test_set": {
        "duration": 0.00021840492263436317,
        "mae": 0.15715716779232025,
        "n_test": 264000,
        "cn_2_mae": 0.4259568750858307,
        "cn_3_mae": 0.14907699823379517,
        "cn_4_mae": 0.13302549719810486
      },
      "train_set": {
        "duration": 0.00028641708195209503,
        "mae": 0.001366154756397009,
        "n_test": 1000,
        "cn_2_mae": 0.00032369079417549074,
        "cn_3_mae": 0.000987877487204969,
        "cn_4_mae": 0.0028403145261108875
      }
    }
  }
}